setup.py
django_summit.egg-info/PKG-INFO
django_summit.egg-info/SOURCES.txt
django_summit.egg-info/dependency_links.txt
django_summit.egg-info/top_level.txt
summit/__init__.py
summit/linaro_settings.py
summit/manage.py
summit/settings.py
summit/ubuntu_settings.py
summit/urls.py
summit/common/__init__.py
summit/common/context_processors.py
summit/common/forms.py
summit/common/models.py
summit/common/tests.py
summit/common/utils.py
summit/common/views.py
summit/common/admin/__init__.py
summit/common/admin/menuadmin.py
summit/common/management/__init__.py
summit/common/management/commands/__init__.py
summit/common/management/commands/init-summit.py
summit/common/management/commands/lpupdate.py
summit/common/management/commands/release.py
summit/common/migrations/0001_add_custom_menus.py
summit/common/migrations/__init__.py
summit/common/templatetags/__init__.py
summit/common/templatetags/menubuilder.py
summit/extra/__init__.py
summit/extra/fields/__init__.py
summit/extra/fields/countryfield.py
summit/extra/formsets/__init__.py
summit/extra/formsets/wizardformset.py
summit/schedule/__init__.py
summit/schedule/autoslug.py
summit/schedule/context_processors.py
summit/schedule/decorators.py
summit/schedule/fields.py
summit/schedule/forms.py
summit/schedule/launchpad.py
summit/schedule/render.py
summit/schedule/tests.py
summit/schedule/views.py
summit/schedule/admin/__init__.py
summit/schedule/admin/agendaadmin.py
summit/schedule/admin/attendeeadmin.py
summit/schedule/admin/crewadmin.py
summit/schedule/admin/leadadmin.py
summit/schedule/admin/meetingadmin.py
summit/schedule/admin/roomadmin.py
summit/schedule/admin/slotadmin.py
summit/schedule/admin/summitadmin.py
summit/schedule/management/__init__.py
summit/schedule/management/commands/__init__.py
summit/schedule/management/commands/autoschedule.py
summit/schedule/management/commands/checkschedule.py
summit/schedule/management/commands/deadblueprints.py
summit/schedule/management/commands/fixtimeoffset.py
summit/schedule/management/commands/import_live_data.py
summit/schedule/management/commands/initslots.py
summit/schedule/management/commands/randomise.py
