Metadata-Version: 1.0
Name: django-summit
Version: 1.1.-
Summary: This is the Summit Scheduling Tool
Home-page: http://launchpad.net/summit
Author: Chris Johnston
Author-email: chrisjohnston@ubuntu.com
License: UNKNOWN
Platform: UNKNOWN
